bag_cross_validate/__init__.py
bag_cross_validate/bag_cross_validate.py
bag_cross_validate/bag_cross_validate_example.py
bag_cross_validate/bag_cross_validate_test.py
bag_cross_validate-0.0.3.dist-info/LICENSE
bag_cross_validate-0.0.3.dist-info/METADATA
bag_cross_validate-0.0.3.dist-info/WHEEL
bag_cross_validate-0.0.3.dist-info/top_level.txt
bag_cross_validate-0.0.3.dist-info/RECORD
