Metadata-Version: 2.1
Name: bag-cross-validate
Version: 0.0.3
Summary: Perform cross-validation on MIL data using sklearn. Assume single-instance inference for the bag label
Home-page: https://github.com/johnvorsten/bag-cross-validate
Author: John Vorsten
Author-email: vorstenjohn@gmail.com
License: UNKNOWN
Project-URL: Bug Tracker, https://github.com/johnvorsten/bag-cross-validate/issues
Platform: UNKNOWN
Classifier: Programming Language :: Python :: 3
Classifier: License :: OSI Approved :: MIT License
Classifier: Operating System :: OS Independent
Requires-Python: >=3.6
License-File: LICENSE
